Metadata-Version: 2.1
Name: image2square
Version: 1.0.0
Summary: Takes an image and force it into a square with gaussian blurred background as filler.
Home-page: https://github.com/sethblack/python-image-to-square
Author: Seth Black
Author-email: sblack@sethserver.com
License: UNKNOWN
Platform: UNKNOWN
Classifier: Programming Language :: Python
Classifier: Programming Language :: Python :: 3
Classifier: Programming Language :: Python :: 3 :: Only
Classifier: Development Status :: 5 - Production/Stable
Classifier: Environment :: Console
Classifier: Intended Audience :: Developers
Classifier: Operating System :: OS Independent
